tw_invoice/__init__.py
tw_invoice/app_client.py
tw_invoice/carrier.py
tw_invoice/exception.py
tw_invoice/schema.py
tw_invoice/utils.py
tw_invoice-2023.9.6.dist-info/LICENSE
tw_invoice-2023.9.6.dist-info/WHEEL
tw_invoice-2023.9.6.dist-info/METADATA
tw_invoice-2023.9.6.dist-info/RECORD
