Metadata-Version: 2.1
Name: tw_invoice
Version: 2023.9.6
Summary: 🇹🇼🧾 Python SDK for accessing Taiwan E-Inovice API
Keywords: taiwan,tw,invoice,tax,taxation,tax-invoice,invoice-api
Author-email: Tomy Hsieh <pypi@tomy.me>
Requires-Python: ~=3.7
Classifier: Development Status :: 4 - Beta
Classifier: Intended Audience :: Developers
Classifier: Intended Audience :: Financial and Insurance Industry
Classifier: Intended Audience :: Information Technology
Classifier: Operating System :: OS Independent
Classifier: License :: OSI Approved :: MIT License
Classifier: Programming Language :: Python :: 3.7
Classifier: Programming Language :: Python :: 3.8
Classifier: Programming Language :: Python :: 3.9
Classifier: Programming Language :: Python :: 3.10
Classifier: Topic :: Office/Business :: Financial :: Accounting
Classifier: Topic :: Software Development :: Libraries
Classifier: Topic :: Software Development :: Libraries :: Python Modules
Requires-Dist: requests >=2.6
Requires-Dist: pydantic >=1.5
Requires-Dist: black ~=22.1.0 ; extra == "dev"
Requires-Dist: isort ~=5.3.0 ; extra == "dev"
Requires-Dist: flake8 ~=3.8.0 ; extra == "dev"
Requires-Dist: pytest >=2.7.3 ; extra == "test"
Requires-Dist: pytest-cov >=3.0.0 ; extra == "test"
Requires-Dist: pytest-mock >=3.0.0 ; extra == "test"
Project-URL: Source, https://github.com/tomy0000000/tw-invoice
Project-URL: Tracker, https://github.com/tomy0000000/tw-invoice/issues
Provides-Extra: dev
Provides-Extra: test
